odoo8_addon_purchase_request_procurement-8.0.1.0.0.99.dev18-py3.8-nspkg.pth
odoo_addons/purchase_request_procurement/README.rst
odoo_addons/purchase_request_procurement/__init__.py
odoo_addons/purchase_request_procurement/__openerp__.py
odoo_addons/purchase_request_procurement/i18n/ca.po
odoo_addons/purchase_request_procurement/i18n/de.po
odoo_addons/purchase_request_procurement/i18n/es.po
odoo_addons/purchase_request_procurement/i18n/es_MX.po
odoo_addons/purchase_request_procurement/i18n/fi.po
odoo_addons/purchase_request_procurement/i18n/fr.po
odoo_addons/purchase_request_procurement/i18n/fr_CH.po
odoo_addons/purchase_request_procurement/i18n/hr.po
odoo_addons/purchase_request_procurement/i18n/hr_HR.po
odoo_addons/purchase_request_procurement/i18n/it.po
odoo_addons/purchase_request_procurement/i18n/pt_BR.po
odoo_addons/purchase_request_procurement/i18n/pt_PT.po
odoo_addons/purchase_request_procurement/i18n/purchase_request_procurement.pot
odoo_addons/purchase_request_procurement/i18n/ro.po
odoo_addons/purchase_request_procurement/i18n/sk.po
odoo_addons/purchase_request_procurement/i18n/sl.po
odoo_addons/purchase_request_procurement/i18n/tr_TR.po
odoo_addons/purchase_request_procurement/i18n/vi_VN.po
odoo_addons/purchase_request_procurement/i18n/zh_CN.po
odoo_addons/purchase_request_procurement/models/__init__.py
odoo_addons/purchase_request_procurement/models/procurement.py
odoo_addons/purchase_request_procurement/models/product.py
odoo_addons/purchase_request_procurement/models/purchase_request.py
odoo_addons/purchase_request_procurement/static/description/icon.png
odoo_addons/purchase_request_procurement/test/purchase_request_from_procurement.yml
odoo_addons/purchase_request_procurement/views/procurement_view.xml
odoo_addons/purchase_request_procurement/views/product_view.xml
odoo8_addon_purchase_request_procurement-8.0.1.0.0.99.dev18.dist-info/METADATA
odoo8_addon_purchase_request_procurement-8.0.1.0.0.99.dev18.dist-info/WHEEL
odoo8_addon_purchase_request_procurement-8.0.1.0.0.99.dev18.dist-info/namespace_packages.txt
odoo8_addon_purchase_request_procurement-8.0.1.0.0.99.dev18.dist-info/top_level.txt
odoo8_addon_purchase_request_procurement-8.0.1.0.0.99.dev18.dist-info/RECORD
